[
  { "code": "0750647W", "seuil": 40954.942 },
  { "code": "0750648X", "seuil": 40738.994 },
  { "code": "0750653C", "seuil": 40730.823 },
  { "code": "0750667T", "seuil": 40721.267 },
  { "code": "0750660K", "seuil": 40707.968 },
  { "code": "0750683K", "seuil": 40700.227 },
  { "code": "0750693W", "seuil": 40691.609 },
  { "code": "0750652B", "seuil": 40672.751 },
  { "code": "0750680G", "seuil": 40531.641 },
  { "code": "0750714U", "seuil": 40466.493 },
  { "code": "0750657G", "seuil": 40359.57 },
  { "code": "0750664P", "seuil": 40306.79 },
  { "code": "0750656F", "seuil": 40302.531 },
  { "code": "0750663N", "seuil": 40291.147 },
  { "code": "0750704H", "seuil": 40258 },
  { "code": "0750699C", "seuil": 40257.817 },
  { "code": "0750670W", "seuil": 40167.386 },
  { "code": "0750662M", "seuil": 39902.805 },
  { "code": "0750700D", "seuil": 39851.425 },
  { "code": "0750705J", "seuil": 39759 },
  { "code": "0750689S", "seuil": 39708.454 },
  { "code": "0750669V", "seuil": 39660.983 },
  { "code": "0750685M", "seuil": 39647.407 },
  { "code": "0750694X", "seuil": 39491.17 },
  { "code": "0750702F", "seuil": 39454.851 },
  { "code": "0750651A", "seuil": 39154.499 },
  { "code": "0750682J", "seuil": 38954.916 },
  { "code": "0750684L", "seuil": 38954.202 },
  { "code": "0750675B", "seuil": 38813.931 },
  { "code": "0750715V", "seuil": 25850.823 },
  { "code": "0750668U", "seuil": 25311.488 },
  { "code": "0750671X", "seuil": 24551.441 },
  { "code": "0750688R", "seuil": 24276 },
  { "code": "0750703G", "seuil": 22924.391 },
  { "code": "0750712S", "seuil": 22820.853 },
  { "code": "0750711R", "seuil": 22794.411 },
  { "code": "0750692V", "seuil": 17760 },
  { "code": "0750676C", "seuil": 17760 },
  { "code": "0750698B", "seuil": 17760 },
  { "code": "0750673Z", "seuil": 16800 },
  { "code": "0750679F", "seuil": 16800 }
]